sam_onnx/__init__.py
sam_onnx/sam_onnx.py
SAM_ONNX-0.0.3.dist-info/METADATA
SAM_ONNX-0.0.3.dist-info/WHEEL
SAM_ONNX-0.0.3.dist-info/top_level.txt
SAM_ONNX-0.0.3.dist-info/RECORD
